README.md
setup.cfg
setup.py
pyextras/__init__.py
pyextras.egg-info/PKG-INFO
pyextras.egg-info/SOURCES.txt
pyextras.egg-info/dependency_links.txt
pyextras.egg-info/requires.txt
pyextras.egg-info/top_level.txt
pyextras/cache/__init__.py
pyextras/cache/cache.py
pyextras/cache/cachewarnings.py
pyextras/cache/diskcache.py
pyextras/cache/encrypteddiskcache.py
pyextras/cache/errors.py