Metadata-Version: 1.0
Name: pyextras
Version: 0.0.6
Summary: Extra Python utilities.
Home-page: UNKNOWN
Author: Dante Spencer
Author-email: dantespe@umich.edu
License: UNKNOWN
Platform: UNKNOWN
